{
  "version": "1.0.0",
  "project": "TPP Platform",
  "generatedAt": "2026-03-23T12:05:19.333Z",
  "tokens": {
    "colors": {
      "brand": {
        "primary": {
          "value": "#dc2626",
          "type": "color",
          "description": "Primary brand color (red-600)"
        },
        "primaryHover": {
          "value": "#b91c1c",
          "type": "color",
          "description": "Primary hover state"
        },
        "primaryLight": {
          "value": "#fee2e2",
          "type": "color",
          "description": "Primary light background"
        },
        "primaryDark": {
          "value": "#7f1d1d",
          "type": "color",
          "description": "Primary dark variant"
        }
      },
      "semantic": {
        "success": {
          "value": "#22c55e",
          "type": "color",
          "description": "Success states"
        },
        "warning": {
          "value": "#f59e0b",
          "type": "color",
          "description": "Warning states"
        },
        "error": {
          "value": "#ef4444",
          "type": "color",
          "description": "Error states"
        },
        "info": {
          "value": "#3b82f6",
          "type": "color",
          "description": "Info states"
        }
      },
      "status": {
        "doingWell": {
          "value": "#22c55e",
          "type": "color",
          "description": "Student performing well"
        },
        "needsSupport": {
          "value": "#f59e0b",
          "type": "color",
          "description": "Student needs support"
        },
        "atRisk": {
          "value": "#ef4444",
          "type": "color",
          "description": "Student at risk"
        }
      },
      "neutral": {
        "background": {
          "value": "#ffffff",
          "type": "color"
        },
        "foreground": {
          "value": "#0f172a",
          "type": "color"
        },
        "muted": {
          "value": "#f1f5f9",
          "type": "color"
        },
        "border": {
          "value": "#e2e8f0",
          "type": "color"
        }
      }
    },
    "typography": {
      "fontFamily": {
        "sans": {
          "value": [
            "Inter",
            "system-ui",
            "sans-serif"
          ],
          "type": "fontFamily"
        },
        "mono": {
          "value": [
            "Fira Code",
            "monospace"
          ],
          "type": "fontFamily"
        }
      },
      "sizes": {
        "xs": {
          "value": "0.75rem",
          "type": "size"
        },
        "sm": {
          "value": "0.875rem",
          "type": "size"
        },
        "base": {
          "value": "1rem",
          "type": "size"
        },
        "lg": {
          "value": "1.125rem",
          "type": "size"
        },
        "xl": {
          "value": "1.25rem",
          "type": "size"
        },
        "2xl": {
          "value": "1.5rem",
          "type": "size"
        },
        "3xl": {
          "value": "1.875rem",
          "type": "size"
        },
        "4xl": {
          "value": "2.25rem",
          "type": "size"
        }
      },
      "weights": {
        "normal": {
          "value": "400",
          "type": "weight"
        },
        "medium": {
          "value": "500",
          "type": "weight"
        },
        "semibold": {
          "value": "600",
          "type": "weight"
        },
        "bold": {
          "value": "700",
          "type": "weight"
        }
      }
    },
    "spacing": {
      "xs": {
        "value": "0.25rem",
        "type": "spacing"
      },
      "sm": {
        "value": "0.5rem",
        "type": "spacing"
      },
      "md": {
        "value": "1rem",
        "type": "spacing"
      },
      "lg": {
        "value": "1.5rem",
        "type": "spacing"
      },
      "xl": {
        "value": "2rem",
        "type": "spacing"
      },
      "2xl": {
        "value": "3rem",
        "type": "spacing"
      }
    },
    "borderRadius": {
      "sm": {
        "value": "0.25rem",
        "type": "radius"
      },
      "md": {
        "value": "0.5rem",
        "type": "radius"
      },
      "lg": {
        "value": "0.75rem",
        "type": "radius"
      },
      "xl": {
        "value": "1rem",
        "type": "radius"
      },
      "full": {
        "value": "9999px",
        "type": "radius"
      }
    },
    "shadows": {
      "sm": {
        "value": "0 1px 2px 0 rgb(0 0 0 / 0.05)",
        "type": "shadow"
      },
      "md": {
        "value": "0 4px 6px -1px rgb(0 0 0 / 0.1)",
        "type": "shadow"
      },
      "lg": {
        "value": "0 10px 15px -3px rgb(0 0 0 / 0.1)",
        "type": "shadow"
      }
    },
    "animations": {
      "duration": {
        "fast": {
          "value": "150ms",
          "type": "duration"
        },
        "normal": {
          "value": "300ms",
          "type": "duration"
        },
        "slow": {
          "value": "500ms",
          "type": "duration"
        }
      },
      "easing": {
        "default": {
          "value": "cubic-bezier(0.4, 0, 0.2, 1)",
          "type": "easing"
        },
        "in": {
          "value": "cubic-bezier(0.4, 0, 1, 1)",
          "type": "easing"
        },
        "out": {
          "value": "cubic-bezier(0, 0, 0.2, 1)",
          "type": "easing"
        }
      }
    }
  }
}